{
	"configurations" : 
	[
		{
			"directories" : 
			[
				{
					"build" : ".",
					"childIndexes" : 
					[
						1
					],
					"hasInstallRule" : true,
					"jsonFile" : "directory-.-Debug-afadfb8c6fdb43ac9ad5.json",
					"minimumCMakeVersion" : 
					{
						"string" : "3.5"
					},
					"projectIndex" : 0,
					"source" : ".",
					"targetIndexes" : 
					[
						0,
						1,
						2
					]
				},
				{
					"build" : "ServerClient",
					"jsonFile" : "directory-ServerClient-Debug-38e953ad948c66c7f262.json",
					"minimumCMakeVersion" : 
					{
						"string" : "3.12"
					},
					"parentIndex" : 0,
					"projectIndex" : 1,
					"source" : "ServerClient",
					"targetIndexes" : 
					[
						3
					]
				}
			],
			"name" : "Debug",
			"projects" : 
			[
				{
					"childIndexes" : 
					[
						1
					],
					"directoryIndexes" : 
					[
						0
					],
					"name" : "GameZero",
					"targetIndexes" : 
					[
						0,
						1,
						2
					]
				},
				{
					"directoryIndexes" : 
					[
						1
					],
					"name" : "ServerClient",
					"parentIndex" : 0,
					"targetIndexes" : 
					[
						3
					]
				}
			],
			"targets" : 
			[
				{
					"directoryIndex" : 0,
					"id" : "GameZero::@6890427a1f51a3e7e1df",
					"jsonFile" : "target-GameZero-Debug-fa72885937c850ff5579.json",
					"name" : "GameZero",
					"projectIndex" : 0
				},
				{
					"directoryIndex" : 0,
					"id" : "GameZero_autogen::@6890427a1f51a3e7e1df",
					"jsonFile" : "target-GameZero_autogen-Debug-ed59230705275579b405.json",
					"name" : "GameZero_autogen",
					"projectIndex" : 0
				},
				{
					"directoryIndex" : 0,
					"id" : "GameZero_autogen_timestamp_deps::@6890427a1f51a3e7e1df",
					"jsonFile" : "target-GameZero_autogen_timestamp_deps-Debug-da2273a8f3ea271eb8fb.json",
					"name" : "GameZero_autogen_timestamp_deps",
					"projectIndex" : 0
				},
				{
					"directoryIndex" : 1,
					"id" : "ServerClient::@ae412daca24140bbe658",
					"jsonFile" : "target-ServerClient-Debug-c3e98bf967b34b6d0dcd.json",
					"name" : "ServerClient",
					"projectIndex" : 1
				}
			]
		}
	],
	"kind" : "codemodel",
	"paths" : 
	{
		"build" : "/home/draugur/Documents/GameZero/build/c-Debug",
		"source" : "/home/draugur/Documents/GameZero"
	},
	"version" : 
	{
		"major" : 2,
		"minor" : 6
	}
}
